metawebhooksmodels/models/__init__.py
metawebhooksmodels/models/base.py
metawebhooksmodels/models/instagram.py
meta_webhooks_models-0.0.2.dist-info/LICENSE
meta_webhooks_models-0.0.2.dist-info/METADATA
meta_webhooks_models-0.0.2.dist-info/WHEEL
meta_webhooks_models-0.0.2.dist-info/top_level.txt
meta_webhooks_models-0.0.2.dist-info/RECORD
