Metadata-Version: 2.1
Name: meta-webhooks-models
Version: 0.0.2
Summary: Models to handling Meta Webhook payloads
Author-email: Andrea Carmisciano <andrea.carmisciano@gmail.com>
Project-URL: Homepage, https://github.com/acarmisc/meta-webhooks-models
Project-URL: Source, https://github.com/acarmisc/meta-webhooks-models
License-File: LICENSE
Requires-Dist: pydantic~=2.8.2
